taynacclient/__init__.py
taynacclient/client.py
taynacclient/osc/__init__.py
taynacclient/osc/plugin.py
taynacclient/osc/v1/__init__.py
taynacclient/osc/v1/messages.py
taynacclient/tests/__init__.py
taynacclient/tests/unit/__init__.py
taynacclient/tests/unit/v1/__init__.py
taynacclient/tests/unit/v1/fakes.py
taynacclient/tests/unit/v1/test_message.py
taynacclient/v1/__init__.py
taynacclient/v1/client.py
taynacclient/v1/messages.py
taynacclient-1.4.2.dist-info/METADATA
taynacclient-1.4.2.dist-info/WHEEL
taynacclient-1.4.2.dist-info/entry_points.txt
taynacclient-1.4.2.dist-info/pbr.json
taynacclient-1.4.2.dist-info/top_level.txt
taynacclient-1.4.2.dist-info/RECORD
